swandaskcluster/__init__.py
swandaskcluster/_version.py
swandaskcluster/cluster.py
swandaskcluster/config.py
swandaskcluster/jobqueue-swan.yaml
swandaskcluster/security.py
swandaskcluster/utils.py
swandaskcluster-3.1.0.dist-info/LICENSE
swandaskcluster-3.1.0.dist-info/METADATA
swandaskcluster-3.1.0.dist-info/WHEEL
swandaskcluster-3.1.0.dist-info/top_level.txt
swandaskcluster-3.1.0.dist-info/RECORD
